README.rst
setup.py
verktyg_sqlalchemy/__init__.py
verktyg_sqlalchemy.egg-info/PKG-INFO
verktyg_sqlalchemy.egg-info/SOURCES.txt
verktyg_sqlalchemy.egg-info/dependency_links.txt
verktyg_sqlalchemy.egg-info/requires.txt
verktyg_sqlalchemy.egg-info/top_level.txt
verktyg_sqlalchemy/tests/__init__.py