Metadata-Version: 1.1
Name: verktyg-sqlalchemy
Version: 0.1.3
Summary: Library for using sqlalchemy in vertyg applications
Home-page: https://github.com/bwhmather/verktyg-sqlalchemy
Author: Ben Mather
Author-email: bwhmather@bwhmather.com
License: BSD
Platform: any
Classifier: Development Status :: 4 - Beta
Classifier: Environment :: Web Environment
Classifier: Intended Audience :: Developers
Classifier: License :: OSI Approved :: BSD License
Classifier: Operating System :: OS Independent
Classifier: Programming Language :: Python :: 3
Classifier: Topic :: Internet :: WWW/HTTP :: Dynamic Content
Classifier: Topic :: Software Development :: Libraries :: Python Modules
